hello_rock/__init__.py
hello_rock-0.0.1.dist-info/METADATA
hello_rock-0.0.1.dist-info/WHEEL
hello_rock-0.0.1.dist-info/licenses/LICENSE
hello_rock-0.0.1.dist-info/RECORD
