Metadata-Version: 2.4
Name: hello_rock
Version: 0.0.1
Summary: Greet the world!
Author: WnRock
License-Expression: MIT
License-File: LICENSE
Classifier: Operating System :: OS Independent
Classifier: Programming Language :: Python :: 3
Requires-Python: >=3.8
